moyra/__init__.py
moyra/dynamic_model_parameters.py
moyra/helper_funcs.py
moyra/lambdify_extension.py
moyra/model_parameters.py
moyra/numeric_model.py
moyra/symbolic_model.py
moyra/elements/__init__.py
moyra/elements/base_element.py
moyra/elements/damper.py
moyra/elements/flexi_element.py
moyra/elements/mass_matrix.py
moyra/elements/modal_element.py
moyra/elements/rigid_element.py
moyra/elements/spring.py
moyra/forces/__init__.py
moyra/forces/aero_force.py
moyra/forces/composite_force.py
moyra/forces/continuous_grav_force.py
moyra/forces/custom_force.py
moyra/forces/external_force.py
moyra/forces/gravity_force.py
moyra/frames/__init__.py
moyra/frames/base_reference_frame.py
moyra/frames/homogenous_frame.py
moyra/frames/reference_frame.py
moyra/printing/__init__.py
moyra/printing/model.py
moyra-0.3.0.dist-info/METADATA
moyra-0.3.0.dist-info/WHEEL
moyra-0.3.0.dist-info/top_level.txt
moyra-0.3.0.dist-info/RECORD
