Metadata-Version: 2.1
Name: moyra
Version: 0.3.0
Summary: Generate Multi-body Symbolic and Numeric Equations of Motion
Home-page: https://github.com/fh9g12/moyra
Author: Fintan Healy
Author-email: fintan.healy@bristol.ac.uk
License: MIT
Requires-Dist: sympy <=1.12
Requires-Dist: numpy <=1.26
Requires-Dist: scipy
